global_names/__init__.py
global_names/main.py
global_names-0.0.2.dist-info/METADATA
global_names-0.0.2.dist-info/WHEEL
global_names-0.0.2.dist-info/licenses/LICENSE
global_names-0.0.2.dist-info/RECORD
