Metadata-Version: 2.3
Name: global_names
Version: 0.0.2
Summary: Human Names for Synthetic Data Generation
Project-URL: Homepage, https://github.com/DecisionNerd/global_names
Project-URL: Issues, https://github.com/DecisionNerd/global_names/issues
Author-email: David Spencer <hello@frontieranalytica.com>
License-File: LICENSE
Classifier: License :: OSI Approved :: MIT License
Classifier: Operating System :: OS Independent
Classifier: Programming Language :: Python :: 3
Requires-Python: >=3.8
